ghost_wordpack-0.1.1.dist-info/DESCRIPTION.rst
ghost_wordpack-0.1.1.dist-info/METADATA
ghost_wordpack-0.1.1.dist-info/RECORD
ghost_wordpack-0.1.1.dist-info/WHEEL
ghost_wordpack-0.1.1.dist-info/metadata.json
ghost_wordpack-0.1.1.dist-info/top_level.txt
wp/__init__.py
wp/get_words.py
wp/words.py
